client/__init__.py
restaurant_service_client-0.1.0.dist-info/DESCRIPTION.rst
restaurant_service_client-0.1.0.dist-info/METADATA
restaurant_service_client-0.1.0.dist-info/RECORD
restaurant_service_client-0.1.0.dist-info/WHEEL
restaurant_service_client-0.1.0.dist-info/metadata.json
restaurant_service_client-0.1.0.dist-info/top_level.txt
