Metadata-Version: 2.0
Name: restaurant-service-client
Version: 0.1.0
Summary: Restaurant Service Client
Home-page: https://github.com/Kalimaha/restaurant-service-client
Author: Guido Barbaglia
Author-email: guido.barbaglia@gmail.com
License: LICENSE
Platform: UNKNOWN
